income/__init__.py
income/logging.py
income/bpr/__init__.py
income/bpr/model.py
income/bpr/train.py
income/bpr/gpl/__init__.py
income/bpr/gpl/beir.py
income/bpr/gpl/dataset.py
income/bpr/gpl/evaluation.py
income/bpr/gpl/log.py
income/bpr/gpl/loss.py
income/bpr/gpl/mine.py
income/bpr/gpl/mnrl.py
income/bpr/gpl/model.py
income/bpr/gpl/pl.py
income/bpr/gpl/qgen.py
income/bpr/gpl/reformat.py
income/bpr/gpl/rescale.py
income/bpr/gpl/resize.py
income/bpr/gpl/sbert.py
income/jpq/__init__.py
income/jpq/beir_transform.py
income/jpq/dataset.py
income/jpq/init.py
income/jpq/model.py
income/jpq/preprocess.py
income/jpq/robertadot_converter.py
income/jpq/run_init.py
income/jpq/run_train_genq.py
income/jpq/run_train_gpl.py
income/jpq/search.py
income/jpq/tokenize_retrieve.py
income/jpq/train_genq.py
income/jpq/train_gpl.py
income/jpq/beir/__init__.py
income/jpq/beir/evaluate.py
income/jpq/beir/transform.py
income/jpq/models/__init__.py
income/jpq/models/jpq_dual_encoder.py
income/jpq/models/jpqtower_converter.py
income/jpq/models/util.py
income/jpq/models/backbones/__init__.py
income/jpq/models/backbones/bert.py
income/jpq/models/backbones/distilbert.py
income/jpq/models/backbones/roberta.py
income/jpq/models/backbones/roberta_tokenizer.py
income/jpq/models/backbones/util.py
income-0.0.2.dist-info/LICENSE
income-0.0.2.dist-info/METADATA
income-0.0.2.dist-info/WHEEL
income-0.0.2.dist-info/top_level.txt
income-0.0.2.dist-info/RECORD
