Metadata-Version: 2.1
Name: income
Version: 0.0.2
Summary: Domain Adaptation for Memory-Efficient Dense Retrieval
Home-page: https://github.com/NThakur20/income
Author: Nandan Thakur
Author-email: nandant@gmail.com
License: Apache License 2.0
Download-URL: https://github.com/NThakur20/income/archive/v0.0.2.zip
Keywords: Information Retrieval Transformer Networks BERT PyTorch IR NLP deep learning
Platform: UNKNOWN
Classifier: Intended Audience :: Science/Research
Classifier: License :: OSI Approved :: MIT License
Classifier: Programming Language :: Python :: 3.6
Classifier: Topic :: Scientific/Engineering :: Artificial Intelligence
Requires-Python: >=3.6
License-File: LICENSE
Requires-Dist: torch (>=1.9.0)
Requires-Dist: transformers (>=4.3.3)
Requires-Dist: tensorboard (>=2.5.0)
Requires-Dist: boto3
